{
 "Matching": [
  {
   "Id": "864578f6-9ec8-4eec-b61f-bc775ae8e9ba",
   "Type": "Matching",
   "Category": "Golang",
   "Question": {
    "A": "What is the purpose of a function",
    "B": "What is the purpose of a pointer",
    "C": "What is a variable"
   },
   "Options": {
    "1": "a container to hold value",
    "2": "to allow repetitive code to be used throughout the project",
    "3": "to allow change to the memory addres"
   },
   "Answer": {
    "A": "2",
    "B": "3",
    "C": "1"
   }
  },
  {
   "Id": "94f699f0-23ee-4884-8132-668cfe2f2def",
   "Type": "Matching",
   "Category": "Golang",
   "Question": {
    "A": "What is the purpose of a function",
    "B": "What is the purpose of a pointer",
    "C": "What is a variable"
   },
   "Options": {
    "1": "a container to hold value",
    "2": "to allow repetitive code to be used throughout the project",
    "3": "to allow change to the memory addres"
   },
   "Answer": {
    "A": "2",
    "B": "3",
    "C": "1"
   }
  },
  {
   "Id": "509ea931-15cb-40c7-8954-076431ec666f",
   "Type": "Matching",
   "Category": "Golang",
   "Question": {
    "A": "What is the purpose of a function",
    "B": "What is the purpose of a pointer",
    "C": "What is a variable"
   },
   "Options": {
    "1": "a container to hold value",
    "2": "to allow repetitive code to be used throughout the project",
    "3": "to allow change to the memory addres"
   },
   "Answer": {
    "A": "2",
    "B": "3",
    "C": "1"
   }
  }
 ],
 "TrueFalse": [
  {
   "Id": "6fbdaf6e-b671-48cd-82bd-9c7652b8d045",
   "Type": "TrueFalse",
   "Category": "Golang",
   "Question": "Do you know?",
   "Answer": "true"
  },
  {
   "Id": "6a04d034-f681-42a8-b440-b12c5e79c59c",
   "Type": "TrueFalse",
   "Category": "Golang",
   "Question": "Do you know?",
   "Answer": "true"
  },
  {
   "Id": "2443e7fc-6692-44b3-9304-174fc0e78868",
   "Type": "TrueFalse",
   "Category": "Golang",
   "Question": "Do you know?",
   "Answer": "true"
  }
 ],
 "Multiple": [
  {
   "Id": "e1f80138-dec3-4261-99de-4223c8b16c67",
   "Type": "Multiple",
   "Category": "Golang",
   "Question": "Do you know?",
   "Options": {
    "1": "Answer 1",
    "2": "Answer 2",
    "3": "Answer 3",
    "4": "Answer 4"
   },
   "Answer": "1"
  }
 ],
 "Info": [
  {
   "Id": "f5baab4c-4601-4111-b5cb-7959e97e0610",
   "Type": "Info",
   "Category": "golang",
   "Details": "It helps"
  },
  {
   "Id": "ac738336-ee5d-4ff2-86e4-e9706efd1557",
   "Type": "Info",
   "Category": "golang",
   "Details": "It helps"
  },
  {
   "Id": "bcd19e61-965d-4ffb-b660-4c7c06831d30",
   "Type": "Info",
   "Category": "golang",
   "Details": "It helps"
  },
  {
   "Id": "2084eb7a-60c8-400c-9586-f022b4b4401c",
   "Type": "Info",
   "Category": "golang",
   "Details": "It helps"
  }
 ],
 "QandA": [
  {
   "Id": "a39e8edc-0cba-481e-9d3e-56afc5726cbd",
   "Type": "QandA",
   "Category": "Golang",
   "Question": "Do you know?",
   "Answer": "You know right"
  }
 ]
}